codara_model_trainer/__init__.py
codara_model_trainer/trainer.py
codara_model_trainer/trainer_test.py
codara_model_trainer-2.0.0.dist-info/METADATA
codara_model_trainer-2.0.0.dist-info/WHEEL
codara_model_trainer-2.0.0.dist-info/top_level.txt
codara_model_trainer-2.0.0.dist-info/RECORD
