Metadata-Version: 2.1
Name: codara-model-trainer
Version: 2.0.0
Summary: OpenAI Model Trainer and Formatter
